CHANGES.txt
LICENSE.txt
README.txt
bootstrap.py
buildout.cfg
setup.py
src/zope/__init__.py
src/zope.app.keyreference.egg-info/PKG-INFO
src/zope.app.keyreference.egg-info/SOURCES.txt
src/zope.app.keyreference.egg-info/dependency_links.txt
src/zope.app.keyreference.egg-info/namespace_packages.txt
src/zope.app.keyreference.egg-info/not-zip-safe
src/zope.app.keyreference.egg-info/requires.txt
src/zope.app.keyreference.egg-info/top_level.txt
src/zope/app/__init__.py
src/zope/app/keyreference/__init__.py
src/zope/app/keyreference/configure.zcml
src/zope/app/keyreference/interfaces.py
src/zope/app/keyreference/persistent.py
src/zope/app/keyreference/testing.py
src/zope/app/keyreference/tests.py